jasper/__init__.py
jasper_engine-0.0.1.dist-info/LICENSE
jasper_engine-0.0.1.dist-info/METADATA
jasper_engine-0.0.1.dist-info/WHEEL
jasper_engine-0.0.1.dist-info/top_level.txt
jasper_engine-0.0.1.dist-info/RECORD
