Metadata-Version: 2.1
Name: jasper-engine
Version: 0.0.1
Summary: A android reverse tool
Home-page: http://github.com/vforkliu/jasper
Author: forkliu
Author-email: vforkliu@gmail.com
License: UNKNOWN
Keywords: android,unicorn,emulator
Platform: UNKNOWN
Requires-Python: >=3
